par_scrape/__init__.py
par_scrape/__main__.py
par_scrape/crawl.py
par_scrape/enums.py
par_scrape/exceptions.py
par_scrape/extraction_prompt.md
par_scrape/py.typed
par_scrape/scrape_data.py
par_scrape/utils.py
par_scrape-0.8.3.dist-info/METADATA
par_scrape-0.8.3.dist-info/WHEEL
par_scrape-0.8.3.dist-info/entry_points.txt
par_scrape-0.8.3.dist-info/licenses/LICENSE
par_scrape-0.8.3.dist-info/RECORD
