Metadata-Version: 2.4
Name: par_scrape
Version: 0.8.3
Summary: A versatile web scraping tool with options for Selenium or Playwright, featuring OpenAI-powered data extraction and formatting.
Project-URL: Homepage, https://github.com/paulrobello/par_scrape
Project-URL: Documentation, https://github.com/paulrobello/par_scrape/blob/main/README.md
Project-URL: Repository, https://github.com/paulrobello/par_scrape
Project-URL: Issues, https://github.com/paulrobello/par_scrape/issues
Project-URL: Discussions, https://github.com/paulrobello/par_scrape/discussions
Project-URL: Wiki, https://github.com/paulrobello/par_scrape/wiki
Author-email: Paul Robello <probello@gmail.com>
Maintainer-email: Paul Robello <probello@gmail.com>
License: MIT License
License-File: LICENSE
Keywords: anthropic,data extraction,groq,llamacpp,ollama,openai,openrouter,playwright,selenium,web scraping,xai
Classifier: Development Status :: 4 - Beta
Classifier: Environment :: Console
Classifier: Intended Audience :: Developers
Classifier: Intended Audience :: End Users/Desktop
Classifier: Intended Audience :: Other Audience
Classifier: License :: OSI Approved :: MIT License
Classifier: Operating System :: MacOS
Classifier: Operating System :: Microsoft :: Windows :: Windows 10
Classifier: Operating System :: Microsoft :: Windows :: Windows 11
Classifier: Operating System :: POSIX :: Linux
Classifier: Programming Language :: Python :: 3
Classifier: Programming Language :: Python :: 3.11
Classifier: Programming Language :: Python :: 3.12
Classifier: Programming Language :: Python :: 3.13
Classifier: Programming Language :: Python :: 3.14
Classifier: Topic :: Internet :: WWW/HTTP :: Browsers
Classifier: Topic :: Software Development :: Libraries :: Python Modules
Classifier: Topic :: Text Processing :: Markup :: HTML
Classifier: Typing :: Typed
Requires-Python: >=3.11
Requires-Dist: beautifulsoup4>=4.14.2
Requires-Dist: fastapi>=0.121.2
Requires-Dist: openpyxl>=3.1.5
Requires-Dist: pandas>=2.3.3
Requires-Dist: par-ai-core>=0.4.3
Requires-Dist: pydantic>=2.10.6
Requires-Dist: python-dotenv>=1.2.1
Requires-Dist: rich>=14.2.0
Requires-Dist: strenum>=0.4.15
Requires-Dist: tabulate>=0.9.0
Requires-Dist: tldextract>=5.3.0
Requires-Dist: typer>=0.20.0
